mkdocstrings-1.0.2.dist-info/METADATA
mkdocstrings-1.0.2.dist-info/WHEEL
mkdocstrings-1.0.2.dist-info/entry_points.txt
mkdocstrings-1.0.2.dist-info/licenses/LICENSE
mkdocstrings/__init__.py
mkdocstrings/_internal/__init__.py
mkdocstrings/_internal/debug.py
mkdocstrings/_internal/download.py
mkdocstrings/_internal/extension.py
mkdocstrings/_internal/handlers/__init__.py
mkdocstrings/_internal/handlers/base.py
mkdocstrings/_internal/handlers/rendering.py
mkdocstrings/_internal/inventory.py
mkdocstrings/_internal/loggers.py
mkdocstrings/_internal/plugin.py
mkdocstrings/py.typed
mkdocstrings-1.0.2.dist-info/RECORD
