Metadata-Version: 2.4
Name: mkdocstrings
Version: 1.0.2
Summary: Automatic documentation from sources, for MkDocs.
Keywords: mkdocs,mkdocs-plugin,docstrings,autodoc,documentation
Author-Email: =?utf-8?q?Timoth=C3=A9e_Mazzucotelli?= <dev@pawamoy.fr>
License-Expression: ISC
License-File: LICENSE
Classifier: Development Status :: 4 - Beta
Classifier: Intended Audience :: Developers
Classifier: Programming Language :: Python
Classifier: Programming Language :: Python :: 3
Classifier: Programming Language :: Python :: 3 :: Only
Classifier: Programming Language :: Python :: 3.10
Classifier: Programming Language :: Python :: 3.11
Classifier: Programming Language :: Python :: 3.12
Classifier: Programming Language :: Python :: 3.13
Classifier: Programming Language :: Python :: 3.14
Classifier: Topic :: Documentation
Classifier: Topic :: Software Development
Classifier: Topic :: Software Development :: Documentation
Classifier: Topic :: Utilities
Classifier: Typing :: Typed
Project-URL: Homepage, https://mkdocstrings.github.io
Project-URL: Documentation, https://mkdocstrings.github.io
Project-URL: Changelog, https://mkdocstrings.github.io/changelog
Project-URL: Repository, https://github.com/mkdocstrings/mkdocstrings
Project-URL: Issues, https://github.com/mkdocstrings/mkdocstrings/issues
Project-URL: Discussions, https://github.com/mkdocstrings/mkdocstrings/discussions
Project-URL: Gitter, https://gitter.im/mkdocstrings/community
Project-URL: Funding, https://github.com/sponsors/pawamoy
Requires-Python: >=3.10
Requires-Dist: Jinja2>=3.1
Requires-Dist: Markdown>=3.6
Requires-Dist: MarkupSafe>=1.1
Requires-Dist: mkdocs>=1.6
Requires-Dist: mkdocs-autorefs>=1.4
Requires-Dist: pymdown-extensions>=6.3
Provides-Extra: crystal
Requires-Dist: mkdocstrings-crystal>=0.3.4; extra == "crystal"
Provides-Extra: python-legacy
Requires-Dist: mkdocstrings-python-legacy>=0.2.1; extra == "python-legacy"
Provides-Extra: python
Requires-Dist: mkdocstrings-python>=1.16.2; extra == "python"
